{
  "imageFilename": "106.jpg",
  "title": "US Embassy celebrates American Cultural Day",
  "publication": "THE PENINSULA",
  "excerpt": "The US Embassy in Qatar celebrated American Independence Day with an American Cultural Day event featuring panel discussions and cultural exchanges.",
  "category": "event",
  "tags": [
    "US Embassy",
    "American Cultural Day",
    "Qatar-US relations",
    "Independence Day",
    "panel discussion",
    "cultural exchange"
  ],
  "notes": "Publication date not visible; event relates to July 4 celebrations and 50 years of Qatar-US diplomatic relations."
}
